z3c/relationfield/README.rst
z3c/relationfield/__init__.py
z3c/relationfield/configure.zcml
z3c/relationfield/event.py
z3c/relationfield/ftesting.zcml
z3c/relationfield/ftests.py
z3c/relationfield/index.py
z3c/relationfield/interfaces.py
z3c/relationfield/relation.py
z3c/relationfield/schema.py
z3c/relationfield/testing.py
z3c/relationfield/tests.py
z3c_relationfield-3.0.dist-info/LICENSE.txt
z3c_relationfield-3.0.dist-info/METADATA
z3c_relationfield-3.0.dist-info/WHEEL
z3c_relationfield-3.0.dist-info/top_level.txt
z3c_relationfield-3.0.dist-info/RECORD
