Metadata-Version: 2.2
Name: z3c.relationfield
Version: 3.0
Summary: A relation field framework for Zope 3.
Home-page: https://github.com/zopefoundation/z3c.relationfield
Author: Martijn Faassen
Author-email: zope-dev@zope.dev
License: ZPL-2.1
Keywords: relation field
Classifier: Development Status :: 6 - Mature
Classifier: Programming Language :: Python
Classifier: Programming Language :: Python :: 3
Classifier: Programming Language :: Python :: 3.9
Classifier: Programming Language :: Python :: 3.10
Classifier: Programming Language :: Python :: 3.11
Classifier: Programming Language :: Python :: 3.12
Classifier: Programming Language :: Python :: 3.13
Requires-Python: >=3.9
License-File: LICENSE.txt
Requires-Dist: setuptools
Requires-Dist: z3c.objpath>=3
Requires-Dist: zc.relation>=1.0
Requires-Dist: zope.intid
Provides-Extra: test
Requires-Dist: zope.container; extra == "test"
Requires-Dist: zope.copypastemove; extra == "test"
Requires-Dist: zope.site; extra == "test"
Dynamic: author
Dynamic: author-email
Dynamic: classifier
Dynamic: description
Dynamic: home-page
Dynamic: keywords
Dynamic: license
Dynamic: provides-extra
Dynamic: requires-dist
Dynamic: requires-python
Dynamic: summary
